{
    "format_version": "1.10.0",
    "minecraft:client_entity": {
        "description": {
            "identifier": "meraki:dolphin_cp",
            "materials": {
                "default": "entity_alphatest"
            },
            "textures": {
                "default": "textures/tropical_resort/decorations/fuel_canister"
            },
            "geometry": {
                "default": "geometry.fuel_canister"
            },
            "animations": {
                "idle": "animation.fuel_canister.idle"
            },
            "scripts": {
                "animate": [
                    "idle"
                ]
            },
            "render_controllers": ["controller.render.default"],
            "spawn_egg": {
                "texture": "fuel_canister",
                "texture_index": 0
            }
        }
    }
}